{"is_source_file": false, "format": "", "description": "", "external_files": [], "external_methods": [], "published": [], "classes": [], "methods": [], "calls": [], "search-terms": [], "state": 2, "file_id": 12, "knowledge_revision": 18, "git_revision": "f98ce4a6b2e1c07a6b35a02dd201d7adf7c6f4d6", "hash": "1d5ea1b64dea5bb04e1ef2bb7506fc59", "format-version": 4, "code-base-name": "tic_tac_toe_frontend", "filename": "README.md", "revision_history": [{"18": "f98ce4a6b2e1c07a6b35a02dd201d7adf7c6f4d6"}]}